
{
  "header": {
    "reportVersion": 1,
    "event": "Allocation failed - JavaScript heap out of memory",
    "trigger": "FatalError",
    "filename": "report.20191206.154847.864.0.001.json",
    "dumpEventTime": "2019-12-06T15:48:47Z",
    "dumpEventTimeStamp": "1575643727786",
    "processId": 864,
    "cwd": "D:\\GitHub\\BEP_1920_Q2\\front-end",
    "commandLine": [
      "node",
      "C:\\Users\\issah\\AppData\\Roaming\\npm\\\\node_modules\\@angular\\cli\\bin\\ng",
      "lint"
    ],
    "nodejsVersion": "v12.13.1",
    "wordSize": 64,
    "arch": "x64",
    "platform": "win32",
    "componentVersions": {
      "node": "12.13.1",
      "v8": "7.7.299.13-node.16",
      "uv": "1.33.1",
      "zlib": "1.2.11",
      "brotli": "1.0.7",
      "ares": "1.15.0",
      "modules": "72",
      "nghttp2": "1.39.2",
      "napi": "5",
      "llhttp": "1.1.4",
      "http_parser": "2.8.0",
      "openssl": "1.1.1d",
      "cldr": "35.1",
      "icu": "64.2",
      "tz": "2019c",
      "unicode": "12.1"
    },
    "release": {
      "name": "node",
      "lts": "Erbium",
      "headersUrl": "https://nodejs.org/download/release/v12.13.1/node-v12.13.1-headers.tar.gz",
      "sourceUrl": "https://nodejs.org/download/release/v12.13.1/node-v12.13.1.tar.gz",
      "libUrl": "https://nodejs.org/download/release/v12.13.1/win-x64/node.lib"
    },
    "osName": "Windows_NT",
    "osRelease": "10.0.18362",
    "osVersion": "Windows 10 Home",
    "osMachine": "x86_64",
    "cpus": [
      {
        "model": "Intel(R) Core(TM) i7-7700HQ CPU @ 2.80GHz",
        "speed": 2808,
        "user": 5488265,
        "nice": 0,
        "sys": 5434156,
        "idle": 87615843,
        "irq": 1294375
      },
      {
        "model": "Intel(R) Core(TM) i7-7700HQ CPU @ 2.80GHz",
        "speed": 2808,
        "user": 3415140,
        "nice": 0,
        "sys": 2600000,
        "idle": 92522921,
        "irq": 57687
      },
      {
        "model": "Intel(R) Core(TM) i7-7700HQ CPU @ 2.80GHz",
        "speed": 2808,
        "user": 7099265,
        "nice": 0,
        "sys": 3922609,
        "idle": 87516187,
        "irq": 48109
      },
      {
        "model": "Intel(R) Core(TM) i7-7700HQ CPU @ 2.80GHz",
        "speed": 2808,
        "user": 4414328,
        "nice": 0,
        "sys": 2506578,
        "idle": 91617156,
        "irq": 55843
      },
      {
        "model": "Intel(R) Core(TM) i7-7700HQ CPU @ 2.80GHz",
        "speed": 2808,
        "user": 5100796,
        "nice": 0,
        "sys": 3404093,
        "idle": 90033171,
        "irq": 50234
      },
      {
        "model": "Intel(R) Core(TM) i7-7700HQ CPU @ 2.80GHz",
        "speed": 2808,
        "user": 4794531,
        "nice": 0,
        "sys": 3285562,
        "idle": 90457968,
        "irq": 41703
      },
      {
        "model": "Intel(R) Core(TM) i7-7700HQ CPU @ 2.80GHz",
        "speed": 2808,
        "user": 5248765,
        "nice": 0,
        "sys": 4095562,
        "idle": 89193718,
        "irq": 46125
      },
      {
        "model": "Intel(R) Core(TM) i7-7700HQ CPU @ 2.80GHz",
        "speed": 2808,
        "user": 3920281,
        "nice": 0,
        "sys": 2694203,
        "idle": 91923562,
        "irq": 34953
      }
    ],
    "networkInterfaces": [
      {
        "name": "WiFi",
        "internal": false,
        "mac": "88:b1:11:11:80:28",
        "address": "fe80::b0b9:ab82:adf5:b1e2",
        "netmask": "ffff:ffff:ffff:ffff::",
        "family": "IPv6",
        "scopeid": 10
      },
      {
        "name": "WiFi",
        "internal": false,
        "mac": "88:b1:11:11:80:28",
        "address": "192.168.178.51",
        "netmask": "255.255.255.0",
        "family": "IPv4"
      },
      {
        "name": "Loopback Pseudo-Interface 1",
        "internal": true,
        "mac": "00:00:00:00:00:00",
        "address": "::1",
        "netmask": "ffff:ffff:ffff:ffff:ffff:ffff:ffff:ffff",
        "family": "IPv6",
        "scopeid": 0
      },
      {
        "name": "Loopback Pseudo-Interface 1",
        "internal": true,
        "mac": "00:00:00:00:00:00",
        "address": "127.0.0.1",
        "netmask": "255.0.0.0",
        "family": "IPv4"
      }
    ],
    "host": "LAPTOP-IMKKO5JV"
  },
  "javascriptStack": {
    "message": "No stack.",
    "stack": [
      "Unavailable."
    ]
  },
  "nativeStack": [
    {
      "pc": "0x00007ff704f41729",
      "symbol": "std::basic_ostream<char,std::char_traits<char> >::operator<<+10873"
    },
    {
      "pc": "0x00007ff704f45b4c",
      "symbol": "std::basic_ostream<char,std::char_traits<char> >::operator<<+28316"
    },
    {
      "pc": "0x00007ff704f44b08",
      "symbol": "std::basic_ostream<char,std::char_traits<char> >::operator<<+24152"
    },
    {
      "pc": "0x00007ff70503369b",
      "symbol": "v8::base::CPU::has_sse+37723"
    },
    {
      "pc": "0x00007ff7058382de",
      "symbol": "v8::Isolate::ReportExternalAllocationLimitReached+94"
    },
    {
      "pc": "0x00007ff705820321",
      "symbol": "v8::SharedArrayBuffer::Externalize+833"
    },
    {
      "pc": "0x00007ff7056edbec",
      "symbol": "v8::internal::Heap::EphemeronKeyWriteBarrierFromCode+1436"
    },
    {
      "pc": "0x00007ff7056f8f90",
      "symbol": "v8::internal::Heap::ProtectUnprotectedMemoryChunks+1312"
    },
    {
      "pc": "0x00007ff7056f5ac4",
      "symbol": "v8::internal::Heap::PageFlagsAreConsistent+3204"
    },
    {
      "pc": "0x00007ff7056eb353",
      "symbol": "v8::internal::Heap::CollectGarbage+1283"
    },
    {
      "pc": "0x00007ff7056e9b24",
      "symbol": "v8::internal::Heap::AddRetainedMap+2356"
    },
    {
      "pc": "0x00007ff70570adf5",
      "symbol": "v8::internal::Factory::NewFillerObject+53"
    },
    {
      "pc": "0x00007ff705476e19",
      "symbol": "v8::internal::interpreter::JumpTableTargetOffsets::iterator::operator=+4057"
    },
    {
      "pc": "0x00007ff705c6404d",
      "symbol": "v8::internal::SetupIsolateDelegate::SetupHeap+567949"
    },
    {
      "pc": "0x00007ff705c64f81",
      "symbol": "v8::internal::SetupIsolateDelegate::SetupHeap+571841"
    },
    {
      "pc": "0x00000193cb2fd9fe",
      "symbol": ""
    }
  ],
  "javascriptHeap": {
    "totalMemory": 2158305280,
    "totalCommittedMemory": 2158305280,
    "usedMemory": 2147928040,
    "availableMemory": 46711448,
    "memoryLimit": 2197815296,
    "heapSpaces": {
      "read_only_space": {
        "memorySize": 262144,
        "committedMemory": 262144,
        "capacity": 261872,
        "used": 32296,
        "available": 229576
      },
      "new_space": {
        "memorySize": 6291456,
        "committedMemory": 6291456,
        "capacity": 3142464,
        "used": 713448,
        "available": 2429016
      },
      "old_space": {
        "memorySize": 2114564096,
        "committedMemory": 2114564096,
        "capacity": 2112138736,
        "used": 2110738360,
        "available": 1400376
      },
      "code_space": {
        "memorySize": 1212416,
        "committedMemory": 1212416,
        "capacity": 1052768,
        "used": 1052768,
        "available": 0
      },
      "map_space": {
        "memorySize": 1839104,
        "committedMemory": 1839104,
        "capacity": 1409840,
        "used": 1409840,
        "available": 0
      },
      "large_object_space": {
        "memorySize": 33513472,
        "committedMemory": 33513472,
        "capacity": 33430928,
        "used": 33430928,
        "available": 0
      },
      "code_large_object_space": {
        "memorySize": 622592,
        "committedMemory": 622592,
        "capacity": 550400,
        "used": 550400,
        "available": 0
      },
      "new_large_object_space": {
        "memorySize": 0,
        "committedMemory": 0,
        "capacity": 3142464,
        "used": 0,
        "available": 3142464
      }
    }
  },
  "resourceUsage": {
    "userCpuSeconds": 68.14,
    "kernelCpuSeconds": 2.609,
    "cpuConsumptionPercent": 202.14,
    "maxRss": 2244243456,
    "pageFaults": {
      "IORequired": 794827,
      "IONotRequired": 0
    },
    "fsActivity": {
      "reads": 4568,
      "writes": 5
    }
  },
  "libuv": [
  ],
  "environmentVariables": {
    "=D:": "D:\\GitHub\\BEP_1920_Q2\\front-end",
    "=ExitCode": "00000000",
    "dp0": "C:\\Users\\issah\\AppData\\Roaming\\npm\\",
    "platformcode": "KV",
    "LOCALAPPDATA": "C:\\Users\\issah\\AppData\\Local",
    "ProgramFiles": "C:\\Program Files",
    "PROMPT": "$P$G",
    "USERNAME": "issah",
    "CommonProgramFiles": "C:\\Program Files\\Common Files",
    "GOPATH": "C:\\Users\\issah\\go",
    "OnlineServices": "Online Services",
    "FPS_BROWSER_USER_PROFILE_STRING": "Default",
    "MOSQUITTO_DIR": "C:\\Program Files\\mosquitto",
    "NUMBER_OF_PROCESSORS": "8",
    "_prog": "node",
    "__INTELLIJ_COMMAND_HISTFILE__": "C:\\Users\\issah\\.WebStorm2019.2\\config\\terminal\\history\\history-8",
    "SystemDrive": "C:",
    "GRADLE_HOME": "C:\\Users\\issah\\Gradle\\gradle-5.4.1",
    "USERPROFILE": "C:\\Users\\issah",
    "SBT_HOME": "C:\\Program Files (x86)\\sbt\\",
    "PUBLIC": "C:\\Users\\Public",
    "ProgramData": "C:\\ProgramData",
    "OS": "Windows_NT",
    "PROCESSOR_REVISION": "9e09",
    "CommonProgramFiles(x86)": "C:\\Program Files (x86)\\Common Files",
    "MYSQL_HOME": "C:\\Program Files\\MySQL\\MySQL Server 8.0\\bin",
    "CommonProgramW6432": "C:\\Program Files\\Common Files",
    "USERDOMAIN": "LAPTOP-IMKKO5JV",
    "FPS_BROWSER_APP_PROFILE_STRING": "Internet Explorer",
    "PROCESSOR_LEVEL": "6",
    "TEMP": "C:\\Users\\issah\\AppData\\Local\\Temp",
    "IDEA_INITIAL_DIRECTORY": "C:\\Program Files\\JetBrains\\WebStorm 2019.2.4\\bin",
    "=::": "::\\",
    "OPENSSL_CONF": "C:\\OpenSSL-Win32\\bin\\openssl.cfg",
    "ProgramW6432": "C:\\Program Files",
    "APPDATA": "C:\\Users\\issah\\AppData\\Roaming",
    "LOGONSERVER": "\\\\LAPTOP-IMKKO5JV",
    "PSModulePath": "C:\\Program Files\\WindowsPowerShell\\Modules;C:\\WINDOWS\\system32\\WindowsPowerShell\\v1.0\\Modules",
    "PATHEXT": ".COM;.EXE;.BAT;.CMD;.VBS;.VBE;.JSE;.WSF;.WSH;.MSC",
    "GRADLE_USER_HOME": "C:\\Users\\issah\\Gradle\\gradle-5.4.1",
    "TERMINAL_EMULATOR": "JetBrains-JediTerm",
    "JAVA_HOME": "C:\\Program Files\\Java\\jdk1.8.0_144",
    "ChocolateyLastPathUpdate": "Wed Nov 13 09:44:03 2019",
    "SystemRoot": "C:\\WINDOWS",
    "COMPUTERNAME": "LAPTOP-IMKKO5JV",
    "SESSIONNAME": "Console",
    "ProgramFiles(x86)": "C:\\Program Files (x86)",
    "ALLUSERSPROFILE": "C:\\ProgramData",
    "HOMEPATH": "\\Users\\issah",
    "DriverData": "C:\\Windows\\System32\\Drivers\\DriverData",
    "windir": "C:\\WINDOWS",
    "TMP": "C:\\Users\\issah\\AppData\\Local\\Temp",
    "ComSpec": "C:\\WINDOWS\\system32\\cmd.exe",
    "Path": "C:\\ProgramData\\Oracle\\Java\\javapath;C:\\Program Files (x86)\\Intel\\iCLS Client\\;C:\\Program Files\\Intel\\iCLS Client\\;C:\\windows\\system32;C:\\windows;C:\\windows\\System32\\Wbem;C:\\windows\\System32\\WindowsPowerShell\\v1.0\\;C:\\Program Files (x86)\\NVIDIA Corporation\\PhysX\\Common;C:\\Program Files\\MATLAB\\R2017a\\runtime\\win64;C:\\Program Files\\MATLAB\\R2017a\\bin;C:\\Program Files\\Git\\cmd;C:\\WINDOWS\\system32;C:\\WINDOWS;C:\\WINDOWS\\System32\\Wbem;C:\\WINDOWS\\System32\\WindowsPowerShell\\v1.0\\;C:\\Program Files\\MiKTeX 2.9\\miktex\\bin\\x64\\;C:\\Program Files (x86)\\sbt\\bin;C:\\ProgramData\\chocolatey\\bin;C:\\Program Files (x86)\\Windows Live\\Shared;C:\\WINDOWS\\System32\\OpenSSH\\;C:\\Program Files\\Intel\\WiFi\\bin\\;C:\\Program Files\\Common Files\\Intel\\WirelessCommon\\;C:\\Users\\issah\\libsodium;C:\\Go\\bin;C:\\Program Files\\nodejs\\;C:\\Users\\issah\\AppData\\Local\\Programs\\Python\\Python37-32\\Scripts\\;C:\\Users\\issah\\AppData\\Local\\Programs\\Python\\Python37-32\\;C:\\Users\\issah\\AppData\\Local\\Microsoft\\WindowsApps;C:\\Users\\issah\\AppData\\Local\\.meteor;C:\\Users\\issah\\go\\bin;C:\\Users\\issah\\AppData\\Roaming\\npm\\;C:\\Users\\issah\\AppData\\Roaming\\npm",
    "VBOX_MSI_INSTALL_PATH": "C:\\Program Files\\Oracle\\VirtualBox\\",
    "HOMEDRIVE": "C:",
    "PROCESSOR_ARCHITECTURE": "AMD64",
    "ChocolateyInstall": "C:\\ProgramData\\chocolatey",
    "OneDrive": "C:\\Users\\issah\\OneDrive",
    "USERDOMAIN_ROAMINGPROFILE": "LAPTOP-IMKKO5JV",
    "RegionCode": "EMEA",
    "PROCESSOR_IDENTIFIER": "Intel64 Family 6 Model 158 Stepping 9, GenuineIntel"
  },
  "sharedObjects": [
    "C:\\Program Files\\nodejs\\node.exe",
    "C:\\WINDOWS\\SYSTEM32\\ntdll.dll",
    "C:\\Program Files\\AVAST Software\\Avast\\aswhook.dll",
    "C:\\WINDOWS\\System32\\KERNEL32.DLL",
    "C:\\WINDOWS\\System32\\KERNELBASE.dll",
    "C:\\WINDOWS\\System32\\WS2_32.dll",
    "C:\\WINDOWS\\System32\\RPCRT4.dll",
    "C:\\WINDOWS\\System32\\ADVAPI32.dll",
    "C:\\WINDOWS\\System32\\msvcrt.dll",
    "C:\\WINDOWS\\System32\\sechost.dll",
    "C:\\WINDOWS\\System32\\USER32.dll",
    "C:\\WINDOWS\\System32\\win32u.dll",
    "C:\\WINDOWS\\System32\\GDI32.dll",
    "C:\\WINDOWS\\System32\\gdi32full.dll",
    "C:\\WINDOWS\\System32\\msvcp_win.dll",
    "C:\\WINDOWS\\System32\\ucrtbase.dll",
    "C:\\WINDOWS\\System32\\PSAPI.DLL",
    "C:\\WINDOWS\\System32\\CRYPT32.dll",
    "C:\\WINDOWS\\System32\\MSASN1.dll",
    "C:\\WINDOWS\\System32\\bcrypt.dll",
    "C:\\WINDOWS\\SYSTEM32\\dbghelp.dll",
    "C:\\WINDOWS\\SYSTEM32\\IPHLPAPI.DLL",
    "C:\\WINDOWS\\SYSTEM32\\USERENV.dll",
    "C:\\WINDOWS\\System32\\profapi.dll",
    "C:\\WINDOWS\\SYSTEM32\\WINMM.dll",
    "C:\\WINDOWS\\SYSTEM32\\WINMMBASE.dll",
    "C:\\WINDOWS\\System32\\cfgmgr32.dll",
    "C:\\WINDOWS\\System32\\bcryptPrimitives.dll",
    "C:\\WINDOWS\\System32\\IMM32.DLL",
    "C:\\WINDOWS\\System32\\powrprof.dll",
    "C:\\WINDOWS\\System32\\UMPDC.dll",
    "C:\\WINDOWS\\SYSTEM32\\CRYPTBASE.DLL",
    "C:\\WINDOWS\\system32\\uxtheme.dll",
    "C:\\WINDOWS\\System32\\combase.dll",
    "C:\\WINDOWS\\system32\\mswsock.dll",
    "C:\\WINDOWS\\System32\\kernel.appcore.dll",
    "C:\\WINDOWS\\System32\\NSI.dll",
    "C:\\WINDOWS\\SYSTEM32\\dhcpcsvc6.DLL",
    "C:\\WINDOWS\\SYSTEM32\\dhcpcsvc.DLL",
    "C:\\WINDOWS\\SYSTEM32\\DNSAPI.dll",
    "C:\\WINDOWS\\system32\\napinsp.dll",
    "C:\\WINDOWS\\system32\\pnrpnsp.dll",
    "C:\\WINDOWS\\System32\\winrnr.dll",
    "C:\\WINDOWS\\system32\\NLAapi.dll",
    "C:\\WINDOWS\\system32\\wshbth.dll"
  ]
}